.travis.yml
AUTHORS
ChangeLog
README.md
htmlwrite.py
release.md
requirements.txt
setup.cfg
setup.py
test_htmlwrite.py
htmlwrite.egg-info/PKG-INFO
htmlwrite.egg-info/SOURCES.txt
htmlwrite.egg-info/dependency_links.txt
htmlwrite.egg-info/not-zip-safe
htmlwrite.egg-info/pbr.json
htmlwrite.egg-info/requires.txt
htmlwrite.egg-info/top_level.txt