Metadata-Version: 1.1
Name: htmlwrite
Version: 0.6.0
Summary: Write html to a file like object, using a pythonic syntax.
Home-page: https://github.com/garyvdm/htmlwrite
Author: Gary van der Merwe
Author-email: garyvdm@gmail.com
License: Apache-2
Platform: UNKNOWN
Classifier: Development Status :: 4 - Beta
Classifier: Environment :: Web Environment
Classifier: Intended Audience :: Developers
Classifier: Intended Audience :: Information Technology
Classifier: License :: OSI Approved :: Apache Software License
Classifier: Operating System :: OS Independent
Classifier: Programming Language :: Python
Classifier: Topic :: Internet :: WWW/HTTP :: Dynamic Content
